[
    {
        "text": "검정콩밥",
        "label": "rice"
    },
    {
        "text": "계란볶음밥",
        "label": "rice"
    },
    {
        "text": "고추김밥",
        "label": "rice"
    },
    {
        "text": "기장밥",
        "label": "rice"
    },
    {
        "text": "김밥",
        "label": "rice"
    },
    {
        "text": "김치김밥",
        "label": "rice"
    },
    {
        "text": "김치볶음밥",
        "label": "rice"
    },
    {
        "text": "낙지덮밥",
        "label": "rice"
    },
    {
        "text": "날치알김밥",
        "label": "rice"
    },
    {
        "text": "닭고기덮밥",
        "label": "rice"
    },
    {
        "text": "돈까스김밥",
        "label": "rice"
    },
    {
        "text": "돌솥비빔밥",
        "label": "rice"
    },
    {
        "text": "돼지머리국밥",
        "label": "rice"
    },
    {
        "text": "모듬회덮밥",
        "label": "rice"
    },
    {
        "text": "무밥",
        "label": "rice"
    },
    {
        "text": "보리밥",
        "label": "rice"
    },
    {
        "text": "볶음밥",
        "label": "rice"
    },
    {
        "text": "불고기덮밥",
        "label": "rice"
    },
    {
        "text": "비빔밥",
        "label": "rice"
    },
    {
        "text": "새우볶음밥",
        "label": "rice"
    },
    {
        "text": "생선모듬초밥",
        "label": "rice"
    },
    {
        "text": "쇠머리국밥",
        "label": "rice"
    },
    {
        "text": "쇠고기김밥",
        "label": "rice"
    },
    {
        "text": "쇠고기볶음밥",
        "label": "rice"
    },
    {
        "text": "쇠고기주먹밥",
        "label": "rice"
    },
    {
        "text": "수수밥",
        "label": "rice"
    },
    {
        "text": "순대국밥",
        "label": "rice"
    },
    {
        "text": "알밥",
        "label": "rice"
    },
    {
        "text": "영양돌솥밥",
        "label": "rice"
    },
    {
        "text": "오므라이스",
        "label": "rice"
    },
    {
        "text": "오징어덮밥",
        "label": "rice"
    },
    {
        "text": "완두콩밥",
        "label": "rice"
    },
    {
        "text": "유부초밥",
        "label": "rice"
    },
    {
        "text": "육회비빔밥",
        "label": "rice"
    },
    {
        "text": "잡곡밥",
        "label": "rice"
    },
    {
        "text": "잡채밥",
        "label": "rice"
    },
    {
        "text": "제육덮밥",
        "label": "rice"
    },
    {
        "text": "짜장밥",
        "label": "rice"
    },
    {
        "text": "짬뽕밥",
        "label": "rice"
    },
    {
        "text": "차조밥",
        "label": "rice"
    },
    {
        "text": "찰밥",
        "label": "rice"
    },
    {
        "text": "참치김밥",
        "label": "rice"
    },
    {
        "text": "참치마요삼각김밥",
        "label": "rice"
    },
    {
        "text": "참치볶음밥",
        "label": "rice"
    },
    {
        "text": "채소김밥",
        "label": "rice"
    },
    {
        "text": "채소볶음밥",
        "label": "rice"
    },
    {
        "text": "치즈김밥",
        "label": "rice"
    },
    {
        "text": "카레라이스",
        "label": "rice"
    },
    {
        "text": "콩나물국밥",
        "label": "rice"
    },
    {
        "text": "콩나물밥",
        "label": "rice"
    },
    {
        "text": "팥밥",
        "label": "rice"
    },
    {
        "text": "표고버섯볶음밥",
        "label": "rice"
    },
    {
        "text": "하이라이스",
        "label": "rice"
    },
    {
        "text": "현미밥",
        "label": "rice"
    },
    {
        "text": "흑미밥",
        "label": "rice"
    },
    {
        "text": "새우필라프",
        "label": "rice"
    },
    {
        "text": "불고기필라프",
        "label": "rice"
    },
    {
        "text": "고추장불고기 삼각김밥",
        "label": "rice"
    },
    {
        "text": "곤드레나물밥",
        "label": "rice"
    },
    {
        "text": "국밥",
        "label": "rice"
    },
    {
        "text": "농어초밥",
        "label": "rice"
    },
    {
        "text": "돼지국밥",
        "label": "rice"
    },
    {
        "text": "류산슬덮밥",
        "label": "rice"
    },
    {
        "text": "멍게비빔밥",
        "label": "rice"
    },
    {
        "text": "멸치주먹밥",
        "label": "rice"
    },
    {
        "text": "묵밥",
        "label": "rice"
    },
    {
        "text": "문어초밥",
        "label": "rice"
    },
    {
        "text": "비빔밥",
        "label": "rice"
    },
    {
        "text": "삼선볶음밥",
        "label": "rice"
    },
    {
        "text": "새우초밥",
        "label": "rice"
    },
    {
        "text": "새우튀김롤",
        "label": "rice"
    },
    {
        "text": "샐러드김밥",
        "label": "rice"
    },
    {
        "text": "소고기국밥",
        "label": "rice"
    },
    {
        "text": "소고기김밥",
        "label": "rice"
    },
    {
        "text": "송이덮밥",
        "label": "rice"
    },
    {
        "text": "숯불갈비 삼각김밥",
        "label": "rice"
    },
    {
        "text": "약초비빔밥",
        "label": "rice"
    },
    {
        "text": "연어롤",
        "label": "rice"
    },
    {
        "text": "연어초밥",
        "label": "rice"
    },
    {
        "text": "오곡밥",
        "label": "rice"
    },
    {
        "text": "자장밥",
        "label": "rice"
    },
    {
        "text": "잡탕밥",
        "label": "rice"
    },
    {
        "text": "장어덮밥",
        "label": "rice"
    },
    {
        "text": "장어초밥",
        "label": "rice"
    },
    {
        "text": "참치덮밥",
        "label": "rice"
    },
    {
        "text": "참치마요네즈 삼각김밥",
        "label": "rice"
    },
    {
        "text": "충무김밥",
        "label": "rice"
    },
    {
        "text": "캘리포니아롤",
        "label": "rice"
    },
    {
        "text": "한치초밥",
        "label": "rice"
    },
    {
        "text": "해물덮밥",
        "label": "rice"
    },
    {
        "text": "해물볶음밥",
        "label": "rice"
    },
    {
        "text": "회덮밥",
        "label": "rice"
    },
    {
        "text": "트러플 리조또",
        "label": "rice"
    },
    {
        "text": "BBQ갈비라이스",
        "label": "rice"
    },
    {
        "text": "베이컨 크림리조또",
        "label": "rice"
    },
    {
        "text": "새우리조또",
        "label": "rice"
    },
    {
        "text": "낙지리조또",
        "label": "rice"
    },
    {
        "text": "콘치즈그라탕",
        "label": "rice"
    },
    {
        "text": "불고기 크림 리소토",
        "label": "rice"
    },
    {
        "text": "클래식 햄 로제 리소토",
        "label": "rice"
    },
    {
        "text": "쉬림프 도리아",
        "label": "rice"
    },
    {
        "text": "치킨 크림 리조또",
        "label": "rice"
    },
    {
        "text": "스파이시 씨푸드 리조또",
        "label": "rice"
    },
    {
        "text": "로제 펜네 그라탕",
        "label": "rice"
    },
    {
        "text": "치즈 불고기 도리아",
        "label": "rice"
    },
    {
        "text": "채소 초밥",
        "label": "rice"
    }
]
